solrcli/__init__.py
solrcli/commons.py
solrcli/configurations.py
solrcli/helpers.py
solrcli/sanity_checks.py
solrcli-0.1.23.data/scripts/solrcli
solrcli-0.1.23.dist-info/LICENSE
solrcli-0.1.23.dist-info/METADATA
solrcli-0.1.23.dist-info/WHEEL
solrcli-0.1.23.dist-info/top_level.txt
solrcli-0.1.23.dist-info/RECORD
