Metadata-Version: 2.1
Name: solrcli
Version: 0.1.23
Summary: A super simple Solr Cli
Home-page: https://github.com/acarmisc/solrcli
Author: Andrea Carmisciano
Author-email: andrea.carmisciano@gmail.com
License: UNKNOWN
Platform: UNKNOWN
Classifier: Programming Language :: Python :: 3
Classifier: License :: OSI Approved :: MIT License
Classifier: Operating System :: OS Independent
Requires-Dist: certifi
Requires-Dist: chardet (==3.0.4)
Requires-Dist: Click (==7.0)
Requires-Dist: idna (==2.8)
Requires-Dist: PyMySQL
Requires-Dist: pysolr (==3.8.1)
Requires-Dist: PyYAML (==5.1.2)
Requires-Dist: requests (==2.22.0)
Requires-Dist: tqdm (==4.35.0)
Requires-Dist: urllib3 (==1.25.3)
Requires-Dist: xmltodict (==0.12.0)
Requires-Dist: paramiko
Requires-Dist: scp
